refinitiv/__init__.py
refinitiv/dataplatform/__init__.py
refinitiv/dataplatform/configure.py
refinitiv/dataplatform/eikon.py
refinitiv/dataplatform/errors.py
refinitiv/dataplatform/log.py
refinitiv/dataplatform/rdplibconfig.default.json
refinitiv/dataplatform/_external_libraries/__init__.py
refinitiv/dataplatform/_external_libraries/python_configuration/__init__.py
refinitiv/dataplatform/_external_libraries/python_configuration/configuration.py
refinitiv/dataplatform/_external_libraries/python_configuration/configuration_set.py
refinitiv/dataplatform/_external_libraries/python_configuration/helpers.py
refinitiv/dataplatform/content/__init__.py
refinitiv/dataplatform/content/chain/__init__.py
refinitiv/dataplatform/content/chain/chain.py
refinitiv/dataplatform/content/chain/functions.py
refinitiv/dataplatform/content/data/__init__.py
refinitiv/dataplatform/content/data/historical_pricing.py
refinitiv/dataplatform/content/data_grid/__init__.py
refinitiv/dataplatform/content/data_grid/_data.py
refinitiv/dataplatform/content/data_grid/_functions.py
refinitiv/dataplatform/content/data_grid/_fundamental_class.py
refinitiv/dataplatform/content/data_grid/_response.py
refinitiv/dataplatform/content/esg/__init__.py
refinitiv/dataplatform/content/esg/_base_definition.py
refinitiv/dataplatform/content/esg/basic_overview.py
refinitiv/dataplatform/content/esg/data.py
refinitiv/dataplatform/content/esg/data_type.py
refinitiv/dataplatform/content/esg/esg.py
refinitiv/dataplatform/content/esg/full_measures.py
refinitiv/dataplatform/content/esg/full_scores.py
refinitiv/dataplatform/content/esg/response.py
refinitiv/dataplatform/content/esg/standard_measures.py
refinitiv/dataplatform/content/esg/standard_scores.py
refinitiv/dataplatform/content/esg/universe.py
refinitiv/dataplatform/content/fundamental/__init__.py
refinitiv/dataplatform/content/fundamental/fundamental_and_reference.py
refinitiv/dataplatform/content/historical_pricing/__init__.py
refinitiv_dataplatform-1.0.0a21.dist-info/LICENSE.md
refinitiv_dataplatform-1.0.0a21.dist-info/METADATA
refinitiv_dataplatform-1.0.0a21.dist-info/WHEEL
refinitiv_dataplatform-1.0.0a21.dist-info/top_level.txt
refinitiv_dataplatform-1.0.0a21.dist-info/RECORD
