Metadata-Version: 2.1
Name: refinitiv-dataplatform
Version: 1.0.0a21
Summary: Python package for retrieving data.
Home-page: https://developers.refinitiv.com/refinitiv-data-platform/refinitiv-data-platform-libraries
Author: REFINITIV
Author-email: 
License: Apache 2.0
Platform: UNKNOWN
Requires-Python: >3.6
License-File: LICENSE.md
Requires-Dist: httpx (>=0.18.0)
Requires-Dist: nest-asyncio
Requires-Dist: datetime
Requires-Dist: validators
Requires-Dist: pandas (>=1.0.0)
Requires-Dist: numpy (>=1.11.0)
Requires-Dist: appdirs (>=1.4.3)
Requires-Dist: python-dateutil
Requires-Dist: websocket-client (!=1.0.0,>=0.54.0)
Requires-Dist: deprecation
Requires-Dist: python-configuration (!=0.8.0,>=0.7.1)
Requires-Dist: eventemitter (>=0.2.0)
Requires-Dist: watchdog (>=0.10.2)
Requires-Dist: scipy
Requires-Dist: certifi
Requires-Dist: chardet (==3.*)
Requires-Dist: h2 (==3.*)
Requires-Dist: idna (==2.*)
Requires-Dist: rfc3986 (==1.*)
Requires-Dist: requests (==2.*)
